pyya/__init__.py
pyya/__main__.py
pyya/py.typed
pyya-0.1.15.dist-info/METADATA
pyya-0.1.15.dist-info/WHEEL
pyya-0.1.15.dist-info/entry_points.txt
pyya-0.1.15.dist-info/top_level.txt
pyya-0.1.15.dist-info/RECORD
