Metadata-Version: 2.1
Name: pyya
Version: 0.1.15
Summary: Convert YAML/TOML configuration files to Python objects
Author-email: shadowy-pycoder <shadowy-pycoder@example.com>
Project-URL: Homepage, https://github.com/shadowy-pycoder/pyya
Project-URL: Issues, https://github.com/shadowy-pycoder/pyya/issues
Project-URL: Repository, https://github.com/shadowy-pycoder/pyya
Classifier: License :: OSI Approved :: MIT License
Classifier: Operating System :: MacOS :: MacOS X
Classifier: Operating System :: Microsoft :: Windows
Classifier: Operating System :: POSIX :: Linux
Classifier: Programming Language :: Python :: 3
Classifier: Programming Language :: Python :: 3.8
Classifier: Programming Language :: Python :: 3.9
Classifier: Programming Language :: Python :: 3.10
Classifier: Programming Language :: Python :: 3.11
Classifier: Programming Language :: Python :: 3.12
Classifier: Programming Language :: Python :: 3.13
Classifier: Programming Language :: Python :: 3.14
Requires-Python: >=3.8
Requires-Dist: camel-converter >=3.1.2
Requires-Dist: munch >=4.0.0
Requires-Dist: pydantic >=2.5.2
Requires-Dist: pyyaml >=6.0.2
Requires-Dist: toml >=0.10.2
Requires-Dist: types-pyyaml >=6.0.12.20240917
Requires-Dist: types-toml >=0.10.8.20240310
